[{"id":"11","name":"哥斯拉2：怪兽之王","filmAttr":"英语","coverBill":"https://ssl.arkcloudcorp.com/bill/gesila2.png","len":"132","classify":"动作/科幻/冒险/灾难","scheduling":[{"date":"2019-10-14","dateRows":[{"id":"65516710838272","start":"21:00:00","end":"23:12:00","ticketPrice":0.01,"sessionId":"ovYj74rZClsJjYAcxj4s0W0wqQYU","miniCode":"https://ssl.arkcloudcorp.com:443/airTheaterH5/img/790edb1a4a30416f9c4c223e30357345.png"}]},{"date":"2019-10-15","dateRows":[]},{"date":"2019-10-16","dateRows":[]},{"date":"2019-10-17","dateRows":[]},{"date":"2019-10-18","dateRows":[]},{"date":"2019-10-19","dateRows":[]},{"date":"2019-10-20","dateRows":[]}]},{"id":"12","name":"魔女","filmAttr":"韩语","coverBill":"https://ssl.arkcloudcorp.com/bill/monv.png","len":"125","classify":"动作/悬疑","scheduling":[{"date":"2019-10-14","dateRows":[{"id":"66161060790272","start":"21:00:00","end":"23:05:00","ticketPrice":0.01,"sessionId":"ovYj74rZClsJjYAcxj4s0W0wqQYU","miniCode":"https://ssl.arkcloudcorp.com:443/airTheaterH5/img/a0e422e1b38c4e08ad26a6ed2985365d.png"}]},{"date":"2019-10-15","dateRows":[]},{"date":"2019-10-16","dateRows":[]},{"date":"2019-10-17","dateRows":[]},{"date":"2019-10-18","dateRows":[]},{"date":"2019-10-19","dateRows":[]},{"date":"2019-10-20","dateRows":[]}]}]